agent_framework/__init__.py
agent_framework/pinecone/__init__.py
agent_framework_pinecone-0.0.0a1.dist-info/licenses/LICENSE
agent_framework_pinecone-0.0.0a1.dist-info/WHEEL
agent_framework_pinecone-0.0.0a1.dist-info/METADATA
agent_framework_pinecone-0.0.0a1.dist-info/RECORD
